bma423.py
circuitpython_bma423-0.1.0.dist-info/LICENSE
circuitpython_bma423-0.1.0.dist-info/METADATA
circuitpython_bma423-0.1.0.dist-info/WHEEL
circuitpython_bma423-0.1.0.dist-info/top_level.txt
circuitpython_bma423-0.1.0.dist-info/RECORD
