Metadata-Version: 2.1
Name: circuitpython-bma423
Version: 0.1.0
Summary: CircuitPython Driver for the Bosch BMA423 accelerometer included in the lilygo watch
Author-email: "Jose D. Montoya" <jlib@mailmeto.mozmail.com>
License: MIT
Project-URL: Homepage, https://github.com/jposada202020/CircuitPython_BMA423
Keywords: sensor,blinka,circuitpython,micropython,bma423,sensor,accelerometer,BMA423,steps,running,lilygo
Classifier: Intended Audience :: Developers
Classifier: Topic :: Software Development :: Libraries
Classifier: Topic :: Software Development :: Embedded Systems
Classifier: Topic :: System :: Hardware
Classifier: License :: OSI Approved :: MIT License
Classifier: Programming Language :: Python :: 3
License-File: LICENSE
Requires-Dist: Adafruit-Blinka
Requires-Dist: adafruit-circuitpython-busdevice
Requires-Dist: adafruit-circuitpython-register
Provides-Extra: optional
